LICENSE
MANIFEST.in
README.md
setup.py
curie/__init__.py
curie/calibration.py
curie/compound.py
curie/data.py
curie/decay_chain.py
curie/element.py
curie/isotope.py
curie/library.py
curie/plotting.py
curie/reaction.py
curie/spectrum.py
curie/stack.py
curie.egg-info/PKG-INFO
curie.egg-info/SOURCES.txt
curie.egg-info/dependency_links.txt
curie.egg-info/top_level.txt