Metadata-Version: 2.1
Name: curie
Version: 0.0.33
Summary: Curie is a python toolkit to aid in the analysis of experimental nuclear data.
Home-page: https://github.com/jtmorrell/curie
Author: Jonathan Morrell
Author-email: jmorrell@berkeley.edu
License: MIT
License-File: LICENSE
